faa_wechat/__init__.py
faa_wechat/oauth_base/__init__.py
faa_wechat/oauth_base/admin.py
faa_wechat/oauth_base/apis.py
faa_wechat/oauth_base/deps.py
faa_wechat/oauth_base/enums.py
faa_wechat/oauth_base/models.py
faa_wechat/oauth_base/tests.py
faa_wechat/oauth_wechat_applet/README.md
faa_wechat/oauth_wechat_applet/__init__.py
faa_wechat/oauth_wechat_applet/admin.py
faa_wechat/oauth_wechat_applet/apis.py
faa_wechat/oauth_wechat_applet/config.py
faa_wechat/oauth_wechat_applet/deps.py
faa_wechat/oauth_wechat_applet/schemas.py
faa_wechat/oauth_wechat_applet/tests.py
faa_wechat/oauth_wechat_h5/README.md
faa_wechat/oauth_wechat_h5/__init__.py
faa_wechat/oauth_wechat_h5/admin.py
faa_wechat/oauth_wechat_h5/apis.py
faa_wechat/oauth_wechat_h5/config.py
faa_wechat/oauth_wechat_h5/crud.py
faa_wechat/oauth_wechat_h5/deps.py
faa_wechat/oauth_wechat_h5/schemas.py
faa_wechat/oauth_wechat_h5/tests.py
faa_wechat/payment_base/__init__.py
faa_wechat/payment_base/admin.py
faa_wechat/payment_base/apis.py
faa_wechat/payment_base/deps.py
faa_wechat/payment_base/enums.py
faa_wechat/payment_base/models.py
faa_wechat/payment_card/__init__.py
faa_wechat/payment_card/admin.py
faa_wechat/payment_card/models.py
faa_wechat/payment_services/README.md
faa_wechat/payment_services/__init__.py
faa_wechat/payment_services/admin.py
faa_wechat/payment_services/apis.py
faa_wechat/payment_services/crud.py
faa_wechat/payment_services/deps.py
faa_wechat/payment_services/enums.py
faa_wechat/payment_services/events.py
faa_wechat/payment_services/models.py
faa_wechat/payment_wxpay/README.md
faa_wechat/payment_wxpay/__init__.py
faa_wechat/payment_wxpay/admin.py
faa_wechat/payment_wxpay/apis.py
faa_wechat/payment_wxpay/config.py
faa_wechat/payment_wxpay/crud.py
faa_wechat/payment_wxpay/deps.py
faa_wechat/payment_wxpay/schemas.py
faa_wechat/payment_wxpay/tests.py
faa_wechat-0.1.0a1.dist-info/WHEEL
faa_wechat-0.1.0a1.dist-info/METADATA
faa_wechat-0.1.0a1.dist-info/RECORD
